{
  "provinces": [
    { "code": "01", "name": "TP. Hà Nội" },
    { "code": "79", "name": "TP. Hồ Chí Minh" },
    { "code": "31", "name": "TP. Hải Phòng" },
    { "code": "48", "name": "TP. Đà Nẵng" },
    { "code": "92", "name": "TP. Cần Thơ" },
    { "code": "46", "name": "TP. Huế" },
    { "code": "89", "name": "An Giang" },
    { "code": "27", "name": "Bắc Ninh" },
    { "code": "96", "name": "Cà Mau" },
    { "code": "04", "name": "Cao Bằng" },
    { "code": "66", "name": "Đắk Lắk" },
    { "code": "11", "name": "Điện Biên" },
    { "code": "75", "name": "Đồng Nai" },
    { "code": "87", "name": "Đồng Tháp" },
    { "code": "64", "name": "Gia Lai" },
    { "code": "42", "name": "Hà Tĩnh" },
    { "code": "33", "name": "Hưng Yên" },
    { "code": "56", "name": "Khánh Hòa" },
    { "code": "12", "name": "Lai Châu" },
    { "code": "68", "name": "Lâm Đồng" },
    { "code": "20", "name": "Lạng Sơn" },
    { "code": "15", "name": "Lào Cai" },
    { "code": "40", "name": "Nghệ An" },
    { "code": "37", "name": "Ninh Bình" },
    { "code": "25", "name": "Phú Thọ" },
    { "code": "22", "name": "Quảng Ninh" },
    { "code": "51", "name": "Quảng Ngãi" },
    { "code": "44", "name": "Quảng Trị" },
    { "code": "14", "name": "Sơn La" },
    { "code": "72", "name": "Tây Ninh" },
    { "code": "19", "name": "Thái Nguyên" },
    { "code": "38", "name": "Thanh Hóa" },
    { "code": "08", "name": "Tuyên Quang" },
    { "code": "86", "name": "Vĩnh Long" }
  ],
  "districts": {
    "01": [
      { "code": "001", "name": "Quận Ba Đình" },
      { "code": "002", "name": "Quận Hoàn Kiếm" },
      { "code": "003", "name": "Quận Tây Hồ" },
      { "code": "004", "name": "Quận Long Biên" },
      { "code": "005", "name": "Quận Cầu Giấy" },
      { "code": "006", "name": "Quận Đống Đa" },
      { "code": "007", "name": "Quận Hai Bà Trưng" },
      { "code": "008", "name": "Quận Hoàng Mai" },
      { "code": "009", "name": "Quận Thanh Xuân" },
      { "code": "267", "name": "Quận Bắc Từ Liêm" },
      { "code": "268", "name": "Quận Hà Đông" },
      { "code": "010", "name": "Huyện Sóc Sơn" },
      { "code": "011", "name": "Huyện Đông Anh" },
      { "code": "012", "name": "Huyện Gia Lâm" },
      { "code": "013", "name": "Quận Nam Từ Liêm" },
      { "code": "014", "name": "Huyện Thanh Trì" },
      { "code": "269", "name": "Thị xã Sơn Tây" },
      { "code": "270", "name": "Huyện Ba Vì" },
      { "code": "271", "name": "Huyện Phúc Thọ" },
      { "code": "272", "name": "Huyện Đan Phượng" },
      { "code": "273", "name": "Huyện Hoài Đức" },
      { "code": "274", "name": "Huyện Quốc Oai" },
      { "code": "275", "name": "Huyện Mỹ Đức" },
      { "code": "276", "name": "Huyện Ứng Hòa" },
      { "code": "015", "name": "Huyện Oai" },
      { "code": "016", "name": "Huyện Thạch Thất" },
      { "code": "017", "name": "Huyện Chương Mỹ" },
      { "code": "018", "name": "Huyện Thanh Oai" },
      { "code": "019", "name": "Huyện Thường Tín" },
      { "code": "020", "name": "Huyện Phú Xuyên" },
      { "code": "021", "name": "Huyện Mê Linh" }
    ],
    "79": [
      { "code": "769", "name": "TP Thủ Đức" },
      { "code": "760", "name": "Quận 1" },
      { "code": "761", "name": "Quận 12" },
      { "code": "762", "name": "Quận Gò Vấp" },
      { "code": "763", "name": "Quận Bình Thạnh" },
      { "code": "764", "name": "Quận 4" },
      { "code": "765", "name": "Quận 5" },
      { "code": "766", "name": "Quận 6" },
      { "code": "767", "name": "Quận 7" },
      { "code": "768", "name": "Quận 8" },
      { "code": "770", "name": "Quận Tân Bình" },
      { "code": "771", "name": "Quận Tân Phú" },
      { "code": "772", "name": "Quận Phú Nhuận" },
      { "code": "773", "name": "Quận Bình Tân" },
      { "code": "774", "name": "Huyện Củ Chi" },
      { "code": "775", "name": "Huyện Hóc Môn" },
      { "code": "776", "name": "Huyện Bình Chánh" },
      { "code": "777", "name": "Huyện Nhà Bè" },
      { "code": "778", "name": "Huyện Cần Giờ" },
      { "code": "779", "name": "TP Vũng Tàu" },
      { "code": "780", "name": "Thị xã Phú Mỹ" },
      { "code": "781", "name": "Huyện Long Điền" },
      { "code": "782", "name": "Huyện Đất Đỏ" },
      { "code": "783", "name": "Huyện Xuyên Mộc" },
      { "code": "784", "name": "Huyện Châu Đức" },
      { "code": "785", "name": "TP Thủ Dầu Một" },
      { "code": "786", "name": "TP Dĩ An" },
      { "code": "787", "name": "TP Thuận An" },
      { "code": "788", "name": "Thị xã Bến Cát" },
      { "code": "789", "name": "Huyện Bắc Tân Uyên" },
      { "code": "790", "name": "Huyện Bàu Bàng" },
      { "code": "791", "name": "Huyện Dầu Tiếng" }
    ],
    "31": [
      { "code": "303", "name": "Quận Hồng Bàng" },
      { "code": "304", "name": "Quận Ngô Quyền" },
      { "code": "305", "name": "Quận Lê Chân" },
      { "code": "306", "name": "Quận Hải An" },
      { "code": "307", "name": "Quận Kiến An" },
      { "code": "308", "name": "Quận Đồ Sơn" },
      { "code": "309", "name": "Quận Dương Kinh" },
      { "code": "310", "name": "Huyện Thủy Nguyên" },
      { "code": "311", "name": "Huyện An Dương" },
      { "code": "312", "name": "Huyện An Lão" },
      { "code": "313", "name": "Huyện Kiến Thụy" },
      { "code": "314", "name": "Huyện Tiên Lãng" },
      { "code": "315", "name": "Huyện Vĩnh Bảo" },
      { "code": "316", "name": "Huyện Cát Hải" },
      { "code": "317", "name": "Huyện Bạch Long Vĩ" },
      { "code": "318", "name": "TP Hải Dương" },
      { "code": "319", "name": "TP Chí Linh" },
      { "code": "320", "name": "Thị xã Kinh Môn" },
      { "code": "321", "name": "Huyện Nam Sách" },
      { "code": "322", "name": "Huyện Thanh Hà" },
      { "code": "323", "name": "Huyện Cẩm Giàng" },
      { "code": "324", "name": "Huyện Gia Lộc" },
      { "code": "325", "name": "Huyện Tứ Kỳ" },
      { "code": "326", "name": "Huyện Ninh Giang" },
      { "code": "327", "name": "Huyện Thanh Miện" }
    ],
    "48": [
      { "code": "490", "name": "Quận Hải Châu" },
      { "code": "491", "name": "Quận Thanh Khê" },
      { "code": "492", "name": "Quận Sơn Trà" },
      { "code": "493", "name": "Quận Ngũ Hành Sơn" },
      { "code": "494", "name": "Quận Liên Chiểu" },
      { "code": "495", "name": "Quận Cẩm Lệ" },
      { "code": "496", "name": "Huyện Hòa Vang" },
      { "code": "497", "name": "Huyện Hoàng Sa" },
      { "code": "498", "name": "TP Tam Kỳ" },
      { "code": "499", "name": "TP Hội An" },
      { "code": "500", "name": "Thị xã Điện Bàn" },
      { "code": "501", "name": "Huyện Duy Xuyên" },
      { "code": "502", "name": "Huyện Đại Lộc" },
      { "code": "503", "name": "Huyện Quế Sơn" },
      { "code": "504", "name": "Huyện Thăng Bình" },
      { "code": "505", "name": "Huyện Tiên Phước" },
      { "code": "506", "name": "Huyện Nam Giang" },
      { "code": "507", "name": "Huyện Phước Sơn" },
      { "code": "508", "name": "Huyện Hiệp Đức" },
      { "code": "509", "name": "Huyện Nông Sơn" }
    ],
    "92": [
      { "code": "916", "name": "Quận Ninh Kiều" },
      { "code": "917", "name": "Quận Cái Răng" },
      { "code": "918", "name": "Quận Bình Thủy" },
      { "code": "919", "name": "Quận Ô Môn" },
      { "code": "920", "name": "Quận Thốt Nốt" },
      { "code": "921", "name": "Huyện Phong Điền" },
      { "code": "922", "name": "Huyện Cờ Đỏ" },
      { "code": "923", "name": "Huyện Thới Lai" },
      { "code": "924", "name": "Huyện Vĩnh Thạnh" },
      { "code": "925", "name": "TP Sóc Trăng" },
      { "code": "926", "name": "TP Vị Thanh" },
      { "code": "927", "name": "Thị xã Ngã Bảy" },
      { "code": "928", "name": "Huyện Châu Thành (Sóc Trăng)" },
      { "code": "929", "name": "Huyện Mỹ Xuyên" },
      { "code": "930", "name": "Huyện Long Phú" },
      { "code": "931", "name": "Huyện Châu Thành (Hậu Giang)" },
      { "code": "932", "name": "Huyện Phụng Hiệp" }
    ],
    "46": [
      { "code": "474", "name": "TP Huế" },
      { "code": "475", "name": "Thị xã Hương Thủy" },
      { "code": "476", "name": "Thị xã Hương Trà" },
      { "code": "477", "name": "Thị xã Phong Điền" },
      { "code": "478", "name": "Huyện Quảng Điền" },
      { "code": "479", "name": "Huyện A Lưới" },
      { "code": "480", "name": "Huyện Phú Vang" },
      { "code": "481", "name": "Huyện Phú Lộc" },
      { "code": "482", "name": "Huyện Nam Đông" }
    ],

    "15": [
      { "code": "150", "name": "TP Yên Bái" },
      { "code": "151", "name": "TP Lào Cai" },
      { "code": "152", "name": "Thị xã Nghĩa Lộ" },
      { "code": "153", "name": "Huyện Bảo Thắng" },
      { "code": "154", "name": "Huyện Sa Pa" },
      { "code": "155", "name": "Huyện Mù Cang Chải" },
      { "code": "156", "name": "Huyện Văn Chấn" },
      { "code": "157", "name": "Huyện Trấn Yên" },
      { "code": "158", "name": "Huyện Lục Yên" },
      { "code": "159", "name": "Huyện Văn Bàn" },
      { "code": "160", "name": "Huyện Bát Xát" }
    ],
    "37": [
      { "code": "370", "name": "TP Ninh Bình" },
      { "code": "371", "name": "TP Nam Định" },
      { "code": "372", "name": "TP Phủ Lý" },
      { "code": "373", "name": "Thị xã Tam Điệp" },
      { "code": "374", "name": "Huyện Ý Yên" },
      { "code": "375", "name": "Huyện Vụ Bản" },
      { "code": "376", "name": "Huyện Kim Sơn" },
      { "code": "377", "name": "Huyện Gia Viễn" },
      { "code": "378", "name": "Huyện Nho Quan" },
      { "code": "379", "name": "Huyện Hải Hậu" },
      { "code": "380", "name": "Huyện Giao Thủy" },
      { "code": "381", "name": "Huyện Trực Ninh" },
      { "code": "382", "name": "Huyện Duy Tiên" },
      { "code": "383", "name": "Huyện Thanh Liêm" },
      { "code": "384", "name": "Huyện Bình Lục" }
    ],
    "25": [
      { "code": "250", "name": "TP Việt Trì" },
      { "code": "251", "name": "TP Hòa Bình" },
      { "code": "252", "name": "TP Vĩnh Yên" },
      { "code": "253", "name": "Thị xã Phú Thọ" },
      { "code": "254", "name": "Thị xã Phổ Yên" },
      { "code": "255", "name": "Huyện Lâm Thao" },
      { "code": "256", "name": "Huyện Thanh Sơn" },
      { "code": "257", "name": "Huyện Tam Đảo" },
      { "code": "258", "name": "Huyện Mai Châu" },
      { "code": "259", "name": "Huyện Lạc Thủy" },
      { "code": "260", "name": "Huyện Yên Lập" },
      { "code": "261", "name": "Huyện Ba Vì (Hòa Bình cũ)" },
      { "code": "262", "name": "Huyện Đoan Hùng" }
    ],
    "04": [
      { "code": "040", "name": "TP Cao Bằng" },
      { "code": "041", "name": "Huyện Bảo Lâm" },
      { "code": "042", "name": "Huyện Bảo Lạc" },
      { "code": "043", "name": "Huyện Hà Quảng" },
      { "code": "044", "name": "Huyện Trùng Khánh" },
      { "code": "045", "name": "Huyện Hòa An" },
      { "code": "046", "name": "Huyện Quảng Hòa" },
      { "code": "047", "name": "Huyện Thạch An" },
      { "code": "048", "name": "Huyện Nguyên Bình" }
    ]
  },
  "wards": {
    "001": [
      { "code": "00001", "name": "Phúc Xá" },
      { "code": "00004", "name": "Trúc Bạch" },
      { "code": "00007", "name": "Vĩnh Phúc" },
      { "code": "00010", "name": "Cống Vị" }
    ],
    "769": [
      { "code": "26734", "name": "Linh Trung" },
      { "code": "26740", "name": "Linh Chiểu" },
      { "code": "26743", "name": "Hiệp Bình Chánh" },
      { "code": "26746", "name": "Hiệp Bình Phước" }
    ],
    "490": [
      { "code": "20000", "name": "Phường Hải Châu 1" },
      { "code": "20003", "name": "Phường Hải Châu 2" },
      { "code": "20006", "name": "Phường Thạch Thang" }
    ],
    "150": [
      { "code": "33001", "name": "Phường Minh Tân" },
      { "code": "33004", "name": "Phường Yên Thịnh" },
      { "code": "33007", "name": "Phường Nguyễn Thái Học" },
      { "code": "33010", "name": "Xã Tuy Lộc" }
    ],
    "370": [
      { "code": "13001", "name": "Phường Đông Thành" },
      { "code": "13004", "name": "Phường Tân Thành" },
      { "code": "13007", "name": "Phường Bích Đào" },
      { "code": "13010", "name": "Xã Ninh Nhất" }
    ],
    "040": [
      { "code": "01001", "name": "Phường Sông Bằng" },
      { "code": "01004", "name": "Phường Hợp Giang" },
      { "code": "01007", "name": "Phường Tân Giang" },
      { "code": "01010", "name": "Xã Chu Trinh" }
    ]
  }
}